spider2local/__init__.py
spider2local/core/__init__.py
spider2local/core/entity.py
spider2local/core/filter.py
spider2local/core/request.py
spider2local/core/response.py
spider2local/enums/__init__.py
spider2local-0.1.1.dist-info/LICENSE
spider2local-0.1.1.dist-info/METADATA
spider2local-0.1.1.dist-info/WHEEL
spider2local-0.1.1.dist-info/top_level.txt
spider2local-0.1.1.dist-info/RECORD
